kenv/__init__.py
kenv/accelerator.py
kenv/beam.py
kenv/constants.py
kenv/solver.py
kenv-0.3.0.3.dist-info/LICENSE
kenv-0.3.0.3.dist-info/METADATA
kenv-0.3.0.3.dist-info/WHEEL
kenv-0.3.0.3.dist-info/top_level.txt
kenv-0.3.0.3.dist-info/RECORD
