Metadata-Version: 2.1
Name: kenv
Version: 0.3.0.3
Summary: Kapchinscky ENVelope (KENV) -  solver of the Kapchinsky-Vladimirsky envelope equation
Home-page: https://github.com/fuodorov/kenv
Author: Vyacheslav Fedorov
Author-email: fuodorov1998@gmail.com
License: UNKNOWN
Platform: UNKNOWN
Classifier: Programming Language :: Python :: 3
Classifier: License :: OSI Approved :: MIT License
Classifier: Operating System :: OS Independent
Requires-Python: >=3.6
